{
  "comment": "The site's main menu, defined ONCE here. Edit this file to add/remove menu items or dropdown sub-items. Each top-level item has an optional `children` array for its dropdown. URLs starting with '/' are root-relative and get the correct path prefix automatically. Top-level items currently point to homepage sections ('/#legal'); change to a real section page (e.g. '/legal/') once you build one. Sub-item '#' URLs are inert placeholders — replace each with a real path like '/legal/custody/' as you build that page.",
  "items": [
    {
      "label": "Legal",
      "url": "/legal/",
      "children": [
        { "label": "Custody & Visitation", "url": "/legal/custody/" },
        { "label": "Child Support",         "url": "/legal/child-support/" },
        { "label": "Finding Legal Help",    "url": "/legal/finding-legal-help/" }
      ]
    },
    {
      "label": "Financial",
      "url": "/financial/",
      "children": [
        { "label": "Budgeting on One Income", "url": "/financial/budgeting/" },
        { "label": "Assistance Programs",      "url": "/financial/assistance/" },
        { "label": "Funding a Custody Case",   "url": "/financial/funding-custody/" }
      ]
    },
    {
      "label": "Mental",
      "url": "/mental/",
      "children": [
        { "label": "Support Groups", "url": "/mental/support-groups/" },
        { "label": "Counseling",     "url": "/mental/counseling/" },
        { "label": "Helplines",      "url": "/mental/helplines/" }
      ]
    },
    {
      "label": "Resources",
      "url": "/resources/",
      "children": [
        { "label": "Food & Meal Prep",   "url": "/resources/food-meal-prep/" },
        { "label": "Childcare & School", "url": "/resources/childcare-school/" },
        { "label": "Local Resources",    "url": "/resources/local-resources/" }
      ]
    },
    {
      "label": "Reading",
      "url": "/reading/",
      "children": [
        { "label": "Articles", "url": "/reading/articles/" },
        { "label": "Books",    "url": "/reading/books/" },
        { "label": "Podcasts", "url": "/reading/podcasts/" }
      ]
    },
    {
      "label": "Dating",
      "url": "/#dating",
      "children": [
        { "label": "Getting Back Out There", "url": "#" },
        { "label": "App & Site Picks",        "url": "#" }
      ]
    },
    {
      "label": "Merch",
      "url": "/#merch",
      "children": [
        { "label": "The Shop", "url": "#" }
      ]
    }
  ]
}
